setup.py
wenshuo_distributions/Binomialdistribution.py
wenshuo_distributions/Gaussiandistribution.py
wenshuo_distributions/Generaldistribution.py
wenshuo_distributions/__init__.py
wenshuo_distributions.egg-info/PKG-INFO
wenshuo_distributions.egg-info/SOURCES.txt
wenshuo_distributions.egg-info/dependency_links.txt
wenshuo_distributions.egg-info/not-zip-safe
wenshuo_distributions.egg-info/top_level.txt